imogen/__init__.py
imogen/__main__.py
imogen/cli.py
imogen/config.py
imogen/exceptions.py
imogen/iso.py
imogen/util.py
imogen/platform/__init__.py
imogen/platform/aws.py
imogen-0.1.0.dist-info/LICENSE
imogen-0.1.0.dist-info/METADATA
imogen-0.1.0.dist-info/WHEEL
imogen-0.1.0.dist-info/entry_points.txt
imogen-0.1.0.dist-info/top_level.txt
imogen-0.1.0.dist-info/RECORD
