Metadata-Version: 2.1
Name: imogen
Version: 0.1.0
Summary: Imogen system image generator
Author-email: Avram Lubkin <avylove@rockhopper.net>
License: MPLv2.0
Project-URL: Homepage, https://github.com/Rockhopper-Technologies/imogen
Keywords: aws,ami,image
Classifier: Programming Language :: Python :: 3
Classifier: Development Status :: 4 - Beta
Classifier: Environment :: Console
Classifier: Intended Audience :: System Administrators
Classifier: License :: OSI Approved :: Mozilla Public License 2.0 (MPL 2.0)
Classifier: Topic :: System :: Installation/Setup
Requires-Python: >=3.10
License-File: LICENSE
Requires-Dist: boto3
Requires-Dist: botocore
Requires-Dist: enlighten>=1.13
Requires-Dist: pydantic
Requires-Dist: pykickstart
Requires-Dist: requests
Requires-Dist: ruamel.yaml
